setup.py
PyUPnP.egg-info/PKG-INFO
PyUPnP.egg-info/SOURCES.txt
PyUPnP.egg-info/dependency_links.txt
PyUPnP.egg-info/top_level.txt
pyupnp/__init__.py
pyupnp/device.py
pyupnp/event.py
pyupnp/lict.py
pyupnp/logr.py
pyupnp/ssdp.py
pyupnp/upnp.py
pyupnp/util.py
pyupnp/services/__init__.py
pyupnp/services/connection_manager.py
pyupnp/services/content_directory.py
pyupnp/services/microsoft/__init__.py
pyupnp/services/microsoft/media_receiver_registrar.py