Metadata-Version: 1.1
Name: PyUPnP
Version: 0.9b
Summary: Simple Python UPnP device library built in Twisted
Home-page: http://github.com/fuzeman/PyUPnP
Author: Dean Gardiner
Author-email: gardiner91@gmail.com
License: UNKNOWN
Platform: UNKNOWN
Classifier: Programming Language :: Python
Classifier: License :: OSI Approved :: GNU General Public License v3 or later (GPLv3+)
Classifier: Operating System :: OS Independent
Classifier: Development Status :: 4 - Beta
Classifier: Environment :: Other Environment
Classifier: Intended Audience :: Developers
Classifier: Topic :: Software Development :: Libraries :: Python Modules
Classifier: Topic :: System :: Networking
Requires: twisted
Requires: requests
Requires: SOAPpy
